Metadata-Version: 2.1
Name: pyuniqid
Version: 1.2
Summary: A Unique Hexatridecimal ID generator
Home-page: https://github.com/boriskurikhin/pyuniqid
Author: Boris Skurikhin
Author-email: boriskurikhin@gmail.com
License: MIT
Download-URL: https://github.com/boriskurikhin/pyuniqid/archive/v1.2.tar.gz
Keywords: unique,id,unique identifier,hexatridecimal,unique id,uniqid
Platform: UNKNOWN
Classifier: Programming Language :: Python :: 3
Classifier: License :: OSI Approved :: MIT License
Classifier: Operating System :: OS Independent
Requires-Python: >=3.6
